{
  "unversionedId": "concurrency/safe/dead_lock",
  "id": "concurrency/safe/dead_lock",
  "title": "死锁与其他活跃锁",
  "description": "概述",
  "source": "@site/docs/concurrency/safe/2.4并发安全-死锁与其他活跃锁.mdx",
  "sourceDirName": "concurrency/safe",
  "slug": "/concurrency/safe/dead_lock",
  "permalink": "/docs/concurrency/safe/dead_lock",
  "editUrl": "https://github.com/zxuqian/zxuqian.cn/tree/master/docs/concurrency/safe/2.4并发安全-死锁与其他活跃锁.mdx",
  "tags": [],
  "version": "current",
  "lastUpdatedBy": "Author",
  "lastUpdatedAt": 1539502055,
  "formattedLastUpdatedAt": "10/14/2018",
  "frontMatter": {
    "id": "dead_lock",
    "title": "死锁与其他活跃锁"
  },
  "sidebar": "basicSiderBar",
  "previous": {
    "title": "volatile与锁",
    "permalink": "/docs/concurrency/safe/volatile"
  }
}